pandisplay/__init__.py
pandisplay-2.0.0.dist-info/METADATA
pandisplay-2.0.0.dist-info/WHEEL
pandisplay-2.0.0.dist-info/top_level.txt
pandisplay-2.0.0.dist-info/RECORD
