Metadata-Version: 2.1
Name: pandisplay
Version: 2.0.0
Summary: Pandas display methods for DataFrame visualization in Jupyter Notebooks.
Author: bkitej
Requires-Dist: pandas
Requires-Dist: ipython
